data/ding dong.mp3
data/failure.mp3
data/failure.wav
data/home run.mp3
data/session complete.mp3
data/start.mp3
data/start.wav
data/success.mp3
data/test.mp3
data/test.wav
data/victory.mp3
data/yay.mp3
focus/__day__.py
focus/__init__.py
focus/__main__.py
focus/__session__.py
focus/day.py
focus/main.py
focus/session.py
focus/terminal_commands.py
focus/timer.py
focus/timer_backend.py
focus_time-1.2.9.dist-info/LICENSE.txt
focus_time-1.2.9.dist-info/METADATA
focus_time-1.2.9.dist-info/WHEEL
focus_time-1.2.9.dist-info/entry_points.txt
focus_time-1.2.9.dist-info/top_level.txt
focus_time-1.2.9.dist-info/RECORD
