Metadata-Version: 2.1
Name: focus-time
Version: 1.2.9
Summary: Focus time is an Python application that can help you focus for a set amount of time
Home-page: https://github.com/philshams/focus-time
Author: Philip Shamash
Author-email: philip.shamash.17@ucl.ac.uk
License: GNU General Public License
Platform: UNKNOWN
License-File: LICENSE.txt
Requires-Dist: DateTime (>=4.3)
Requires-Dist: numpy (>=1.19)
Requires-Dist: pygame (>=2.1.0)
